Workbook

Sheet Project Introduction
B5: Introduction:
B8: This analysis focuses on GrowX Labs, a SaaS startup offering business automation tools for small startups and SMEs. The platform helps businesses manage leads, automate email marketing, and track sales performance through a monthly subscription model. Currently in its first growth year, GrowX Labs aims to improve marketing efficiency, increase user retention, and scale its recurring revenue sustainably.
B15: Project Objectives:
B18: 1. Analyze user and revenue growth over a 12-month period. 2. Compare the performance and ROI of acquisition channels — Google Ads, Instagram, and Referrals. 3. Measure key metrics including Customer Acquisition Cost (CAC), Lifetime Value (LTV), and Churn Rate. 4. Identify trends in MRR growth and customer retention. 5. Provide data-driven recommendations to optimize marketing spend and accelerate growth.

Sheet 01_Data_Model
C4: Month | D4: Channel | E4: New Users | F4: Active Users | G4: Revenue | H4: Marketing Spend | I4: CAC | J4: ROI | K4: Retention Rate | L4: Churn Rate | M4: LTV | N4: ARPU | O4: MRR
C5: Jan | D5: Google Ads | E5: 320 | F5: 250 | G5: 45000 | H5: 10000 | I5: =IFERROR(H5/E5,0) -> 31.25 | J5: =(G5-H5)/H5 -> 3.5 | K5: =IFERROR(F5/E5,0) -> 0.78125 | L5: =1-K5 -> 0.21875 | M5: =IFERROR(Metrics[[#This Row],[Revenue]]/Metrics[[#This Row],[Active Users]]*(1/Metrics[[#This Row],[Churn Rate]]),0) -> 822.85714 | N5: =IFERROR(Metrics[[#This Row],[Revenue]]/Metrics[[#This Row],[Active Users]],0) -> 180 | O5: =G5*N5 -> 8100000
C6: Jan | D6: Instagram | E6: 180 | F6: 150 | G6: 22000 | H6: 4000 | I6: =IFERROR(H6/E6,0) -> 22.222222 | J6: =(G6-H6)/H6 -> 4.5 | K6: =IFERROR(F6/E6,0) -> 0.83333333 | L6: =1-K6 -> 0.16666667 | M6: =IFERROR(Metrics[[#This Row],[Revenue]]/Metrics[[#This Row],[Active Users]]*(1/Metrics[[#This Row],[Churn Rate]]),0) -> 880 | N6: =IFERROR(Metrics[[#This Row],[Revenue]]/Metrics[[#This Row],[Active Users]],0) -> 146.66667 | O6: =G6*N6 -> 3226666.7
C7: Jan | D7: Referrals | E7: 100 | F7: 95 | G7: 18000 | H7: 2000 | I7: =IFERROR(H7/E7,0) -> 20 | J7: =(G7-H7)/H7 -> 8 | K7: =IFERROR(F7/E7,0) -> 0.95 | L7: =1-K7 -> 0.05 | M7: =IFERROR(Metrics[[#This Row],[Revenue]]/Metrics[[#This Row],[Active Users]]*(1/Metrics[[#This Row],[Churn Rate]]),0) -> 3789.4737 | N7: =IFERROR(Metrics[[#This Row],[Revenue]]/Metrics[[#This Row],[Active Users]],0) -> 189.47368 | O7: =G7*N7 -> 3410526.3
C8: Feb | D8: Google Ads | E8: 400 | F8: 310 | G8: 56000 | H8: 12000 | I8: =IFERROR(H8/E8,0) -> 30 | J8: =(G8-H8)/H8 -> 3.6666667 | K8: =IFERROR(F8/E8,0) -> 0.775 | L8: =1-K8 -> 0.225 | M8: =IFERROR(Metrics[[#This Row],[Revenue]]/Metrics[[#This Row],[Active Users]]*(1/Metrics[[#This Row],[Churn Rate]]),0) -> 802.86738 | N8: =IFERROR(Metrics[[#This Row],[Revenue]]/Metrics[[#This Row],[Active Users]],0) -> 180.64516 | O8: =G8*N8 -> 10116129
C9: Feb | D9: Instagram | E9: 220 | F9: 190 | G9: 26000 | H9: 4500 | I9: =IFERROR(H9/E9,0) -> 20.454545 | J9: =(G9-H9)/H9 -> 4.7777778 | K9: =IFERROR(F9/E9,0) -> 0.86363636 | L9: =1-K9 -> 0.13636364 | M9: =IFERROR(Metrics[[#This Row],[Revenue]]/Metrics[[#This Row],[Active Users]]*(1/Metrics[[#This Row],[Churn Rate]]),0) -> 1003.5088 | N9: =IFERROR(Metrics[[#This Row],[Revenue]]/Metrics[[#This Row],[Active Users]],0) -> 136.84211 | O9: =G9*N9 -> 3557894.7
C10: Feb | D10: Referrals | E10: 130 | F10: 120 | G10: 20000 | H10: 2500 | I10: =IFERROR(H10/E10,0) -> 19.230769 | J10: =(G10-H10)/H10 -> 7 | K10: =IFERROR(F10/E10,0) -> 0.92307692 | L10: =1-K10 -> 0.076923077 | M10: =IFERROR(Metrics[[#This Row],[Revenue]]/Metrics[[#This Row],[Active Users]]*(1/Metrics[[#This Row],[Churn Rate]]),0) -> 2166.6667 | N10: =IFERROR(Metrics[[#This Row],[Revenue]]/Metrics[[#This Row],[Active Users]],0) -> 166.66667 | O10: =G10*N10 -> 3333333.3
C11: Mar | D11: Google Ads | E11: 430 | F11: 340 | G11: 61000 | H11: 12500 | I11: =IFERROR(H11/E11,0) -> 29.069767 | J11: =(G11-H11)/H11 -> 3.88 | K11: =IFERROR(F11/E11,0) -> 0.79069767 | L11: =1-K11 -> 0.20930233 | M11: =IFERROR(Metrics[[#This Row],[Revenue]]/Metrics[[#This Row],[Active Users]]*(1/Metrics[[#This Row],[Churn Rate]]),0) -> 857.18954 | N11: =IFERROR(Metrics[[#This Row],[Revenue]]/Metrics[[#This Row],[Active Users]],0) -> 179.41176 | O11: =G11*N11 -> 10944118
C12: Mar | D12: Instagram | E12: 250 | F12: 215 | G12: 29000 | H12: 4800 | I12: =IFERROR(H12/E12,0) -> 19.2 | J12: =(G12-H12)/H12 -> 5.0416667 | K12: =IFERROR(F12/E12,0) -> 0.86 | L12: =1-K12 -> 0.14 | M12: =IFERROR(Metrics[[#This Row],[Revenue]]/Metrics[[#This Row],[Active Users]]*(1/Metrics[[#This Row],[Churn Rate]]),0) -> 963.45515 | N12: =IFERROR(Metrics[[#This Row],[Revenue]]/Metrics[[#This Row],[Active Users]],0) -> 134.88372 | O12: =G12*N12 -> 3911627.9
C13: Mar | D13: Referrals | E13: 150 | F13: 140 | G13: 23000 | H13: 2700 | I13: =IFERROR(H13/E13,0) -> 18 | J13: =(G13-H13)/H13 -> 7.5185185 | K13: =IFERROR(F13/E13,0) -> 0.93333333 | L13: =1-K13 -> 0.066666667 | M13: =IFERROR(Metrics[[#This Row],[Revenue]]/Metrics[[#This Row],[Active Users]]*(1/Metrics[[#This Row],[Churn Rate]]),0) -> 2464.2857 | N13: =IFERROR(Metrics[[#This Row],[Revenue]]/Metrics[[#This Row],[Active Users]],0) -> 164.28571 | O13: =G13*N13 -> 3778571.4
C14: Apr | D14: Google Ads | E14: 460 | F14: 370 | G14: 67000 | H14: 13000 | I14: =IFERROR(H14/E14,0) -> 28.26087 | J14: =(G14-H14)/H14 -> 4.1538462 | K14: =IFERROR(F14/E14,0) -> 0.80434783 | L14: =1-K14 -> 0.19565217 | M14: =IFERROR(Metrics[[#This Row],[Revenue]]/Metrics[[#This Row],[Active Users]]*(1/Metrics[[#This Row],[Churn Rate]]),0) -> 925.52553 | N14: =IFERROR(Metrics[[#This Row],[Revenue]]/Metrics[[#This Row],[Active Users]],0) -> 181.08108 | O14: =G14*N14 -> 12132432
C15: Apr | D15: Instagram | E15: 280 | F15: 245 | G15: 33000 | H15: 5000 | I15: =IFERROR(H15/E15,0) -> 17.857143 | J15: =(G15-H15)/H15 -> 5.6 | K15: =IFERROR(F15/E15,0) -> 0.875 | L15: =1-K15 -> 0.125 | M15: =IFERROR(Metrics[[#This Row],[Revenue]]/Metrics[[#This Row],[Active Users]]*(1/Metrics[[#This Row],[Churn Rate]]),0) -> 1077.551 | N15: =IFERROR(Metrics[[#This Row],[Revenue]]/Metrics[[#This Row],[Active Users]],0) -> 134.69388 | O15: =G15*N15 -> 4444898
C16: Apr | D16: Referrals | E16: 180 | F16: 165 | G16: 26000 | H16: 3000 | I16: =IFERROR(H16/E16,0) -> 16.666667 | J16: =(G16-H16)/H16 -> 7.6666667 | K16: =IFERROR(F16/E16,0) -> 0.91666667 | L16: =1-K16 -> 0.083333333 | M16: =IFERROR(Metrics[[#This Row],[Revenue]]/Metrics[[#This Row],[Active Users]]*(1/Metrics[[#This Row],[Churn Rate]]),0) -> 1890.9091 | N16: =IFERROR(Metrics[[#This Row],[Revenue]]/Metrics[[#This Row],[Active Users]],0) -> 157.57576 | O16: =G16*N16 -> 4096969.7
... C40: Dec | D40: Referrals | E40: 280 | F40: 255 | G40: 40000 | H40: 4300 | I40: =IFERROR(H40/E40,0) -> 15.357143 | J40: =(G40-H40)/H40 -> 8.3023256 | K40: =IFERROR(F40/E40,0) -> 0.91071429 | L40: =1-K40 -> 0.089285714 | M40: =IFERROR(Metrics[[#This Row],[Revenue]]/Metrics[[#This Row],[Active Users]]*(1/Metrics[[#This Row],[Churn Rate]]),0) -> 1756.8627 | N40: =IFERROR(Metrics[[#This Row],[Revenue]]/Metrics[[#This Row],[Active Users]],0) -> 156.86275 | O40: =G40*N40 -> 6274509.8

Sheet 02_Processed_Data
C4: Month | D4: New Users | E4: Active Users | F4: Revenue | G4: Marketing Spend | H4: CAC | I4: ROI | J4: Retention Rate | K4: Churn Rate | L4: LTV
C5: Jan | D5: =IFERROR(SUM('01_Data_Model'!E5:E7),0) -> 600 | E5: =IFERROR(SUM('01_Data_Model'!F5:F7),0) -> 495 | F5: =IFERROR(SUM('01_Data_Model'!G5:G7),0) -> 85000 | G5: =IFERROR(SUM('01_Data_Model'!H5:H7),0) -> 16000 | H5: =IFERROR(G5/D5,0) -> 26.666667 | I5: =IFERROR((F5-G5)/G5,0) -> 4.3125 | J5: =IFERROR(E5/D5,0) -> 0.825 | K5: =IFERROR(1-J5,0) -> 0.175 | L5: =Monthy_Metrics[[#This Row],[Revenue]]/Monthy_Metrics[[#This Row],[Active Users]]*(1/(Monthy_Metrics[[#This Row],[Churn Rate]])) -> 981.24098
C6: Feb | D6: =IFERROR(SUM('01_Data_Model'!E8:E10),0) -> 750 | E6: =IFERROR(SUM('01_Data_Model'!F8:F10),0) -> 620 | F6: =IFERROR(SUM('01_Data_Model'!G8:G10),0) -> 102000 | G6: =IFERROR(SUM('01_Data_Model'!H8:H10),0) -> 19000 | H6: =IFERROR(G6/D6,0) -> 25.333333 | I6: =IFERROR((F6-G6)/G6,0) -> 4.3684211 | J6: =IFERROR(E6/D6,0) -> 0.82666667 | K6: =IFERROR(1-J6,0) -> 0.17333333 | L6: =Monthy_Metrics[[#This Row],[Revenue]]/Monthy_Metrics[[#This Row],[Active Users]]*(1/(Monthy_Metrics[[#This Row],[Churn Rate]])) -> 949.13151
C7: Mar | D7: =IFERROR(SUM('01_Data_Model'!E11:E13),0) -> 830 | E7: =IFERROR(SUM('01_Data_Model'!F11:F13),0) -> 695 | F7: =IFERROR(SUM('01_Data_Model'!G11:G13),0) -> 113000 | G7: =IFERROR(SUM('01_Data_Model'!H11:H13),0) -> 20000 | H7: =IFERROR(G7/D7,0) -> 24.096386 | I7: =IFERROR((F7-G7)/G7,0) -> 4.65 | J7: =IFERROR(E7/D7,0) -> 0.8373494 | K7: =IFERROR(1-J7,0) -> 0.1626506 | L7: =Monthy_Metrics[[#This Row],[Revenue]]/Monthy_Metrics[[#This Row],[Active Users]]*(1/(Monthy_Metrics[[#This Row],[Churn Rate]])) -> 999.62697
C8: Apr | D8: =IFERROR(SUM('01_Data_Model'!E14:E16),0) -> 920 | E8: =IFERROR(SUM('01_Data_Model'!F14:F16),0) -> 780 | F8: =IFERROR(SUM('01_Data_Model'!G14:G16),0) -> 126000 | G8: =IFERROR(SUM('01_Data_Model'!H14:H16),0) -> 21000 | H8: =IFERROR(G8/D8,0) -> 22.826087 | I8: =IFERROR((F8-G8)/G8,0) -> 5 | J8: =IFERROR(E8/D8,0) -> 0.84782609 | K8: =IFERROR(1-J8,0) -> 0.15217391 | L8: =Monthy_Metrics[[#This Row],[Revenue]]/Monthy_Metrics[[#This Row],[Active Users]]*(1/(Monthy_Metrics[[#This Row],[Churn Rate]])) -> 1061.5385
C9: May | D9: =IFERROR(SUM('01_Data_Model'!E17:E19),0) -> 990 | E9: =IFERROR(SUM('01_Data_Model'!F17:F19),0) -> 845 | F9: =IFERROR(SUM('01_Data_Model'!G17:G19),0) -> 137000 | G9: =IFERROR(SUM('01_Data_Model'!H17:H19),0) -> 21900 | H9: =IFERROR(G9/D9,0) -> 22.121212 | I9: =IFERROR((F9-G9)/G9,0) -> 5.2557078 | J9: =IFERROR(E9/D9,0) -> 0.85353535 | K9: =IFERROR(1-J9,0) -> 0.14646465 | L9: =Monthy_Metrics[[#This Row],[Revenue]]/Monthy_Metrics[[#This Row],[Active Users]]*(1/(Monthy_Metrics[[#This Row],[Churn Rate]])) -> 1106.9578
C10: Jun | D10: =IFERROR(SUM('01_Data_Model'!E20:E22),0) -> 1050 | E10: =IFERROR(SUM('01_Data_Model'!F20:F22),0) -> 890 | F10: =IFERROR(SUM('01_Data_Model'!G20:G22),0) -> 147000 | G10: =IFERROR(SUM('01_Data_Model'!H20:H22),0) -> 22900 | H10: =IFERROR(G10/D10,0) -> 21.809524 | I10: =IFERROR((F10-G10)/G10,0) -> 5.419214 | J10: =IFERROR(E10/D10,0) -> 0.84761905 | K10: =IFERROR(1-J10,0) -> 0.15238095 | L10: =Monthy_Metrics[[#This Row],[Revenue]]/Monthy_Metrics[[#This Row],[Active Users]]*(1/(Monthy_Metrics[[#This Row],[Churn Rate]])) -> 1083.9185
C11: Jul | D11: =IFERROR(SUM('01_Data_Model'!E23:E25),0) -> 1100 | E11: =IFERROR(SUM('01_Data_Model'!F23:F25),0) -> 935 | F11: =IFERROR(SUM('01_Data_Model'!G23:G25),0) -> 157000 | G11: =IFERROR(SUM('01_Data_Model'!H23:H25),0) -> 23900 | H11: =IFERROR(G11/D11,0) -> 21.727273 | I11: =IFERROR((F11-G11)/G11,0) -> 5.5690377 | J11: =IFERROR(E11/D11,0) -> 0.85 | K11: =IFERROR(1-J11,0) -> 0.15 | L11: =Monthy_Metrics[[#This Row],[Revenue]]/Monthy_Metrics[[#This Row],[Active Users]]*(1/(Monthy_Metrics[[#This Row],[Churn Rate]])) -> 1119.4296
C12: Aug | D12: =IFERROR(SUM('01_Data_Model'!E26:E28),0) -> 1160 | E12: =IFERROR(SUM('01_Data_Model'!F26:F28),0) -> 975 | F12: =IFERROR(SUM('01_Data_Model'!G26:G28),0) -> 165000 | G12: =IFERROR(SUM('01_Data_Model'!H26:H28),0) -> 24800 | H12: =IFERROR(G12/D12,0) -> 21.37931 | I12: =IFERROR((F12-G12)/G12,0) -> 5.6532258 | J12: =IFERROR(E12/D12,0) -> 0.84051724 | K12: =IFERROR(1-J12,0) -> 0.15948276 | L12: =Monthy_Metrics[[#This Row],[Revenue]]/Monthy_Metrics[[#This Row],[Active Users]]*(1/(Monthy_Metrics[[#This Row],[Churn Rate]])) -> 1061.1227
C13: Sep | D13: =IFERROR(SUM('01_Data_Model'!E29:E31),0) -> 1200 | E13: =IFERROR(SUM('01_Data_Model'!F29:F31),0) -> 1005 | F13: =IFERROR(SUM('01_Data_Model'!G29:G31),0) -> 172000 | G13: =IFERROR(SUM('01_Data_Model'!H29:H31),0) -> 25400 | H13: =IFERROR(G13/D13,0) -> 21.166667 | I13: =IFERROR((F13-G13)/G13,0) -> 5.7716535 | J13: =IFERROR(E13/D13,0) -> 0.8375 | K13: =IFERROR(1-J13,0) -> 0.1625 | L13: =Monthy_Metrics[[#This Row],[Revenue]]/Monthy_Metrics[[#This Row],[Active Users]]*(1/(Monthy_Metrics[[#This Row],[Churn Rate]])) -> 1053.1956
C14: Oct | D14: =IFERROR(SUM('01_Data_Model'!E32:E34),0) -> 1240 | E14: =IFERROR(SUM('01_Data_Model'!F32:F34),0) -> 1045 | F14: =IFERROR(SUM('01_Data_Model'!G32:G34),0) -> 179000 | G14: =IFERROR(SUM('01_Data_Model'!H32:H34),0) -> 25900 | H14: =IFERROR(G14/D14,0) -> 20.887097 | I14: =IFERROR((F14-G14)/G14,0) -> 5.9111969 | J14: =IFERROR(E14/D14,0) -> 0.84274194 | K14: =IFERROR(1-J14,0) -> 0.15725806 | L14: =Monthy_Metrics[[#This Row],[Revenue]]/Monthy_Metrics[[#This Row],[Active Users]]*(1/(Monthy_Metrics[[#This Row],[Churn Rate]])) -> 1089.2406
C15: Nov | D15: =IFERROR(SUM('01_Data_Model'!E35:E37),0) -> 1270 | E15: =IFERROR(SUM('01_Data_Model'!F35:F37),0) -> 1075 | F15: =IFERROR(SUM('01_Data_Model'!G35:G37),0) -> 184000 | G15: =IFERROR(SUM('01_Data_Model'!H35:H37),0) -> 26200 | H15: =IFERROR(G15/D15,0) -> 20.629921 | I15: =IFERROR((F15-G15)/G15,0) -> 6.0229008 | J15: =IFERROR(E15/D15,0) -> 0.84645669 | K15: =IFERROR(1-J15,0) -> 0.15354331 | L15: =Monthy_Metrics[[#This Row],[Revenue]]/Monthy_Metrics[[#This Row],[Active Users]]*(1/(Monthy_Metrics[[#This Row],[Churn Rate]])) -> 1114.7525
C16: Dec | D16: =IFERROR(SUM('01_Data_Model'!E38:E40),0) -> 1310 | E16: =IFERROR(SUM('01_Data_Model'!F38:F40),0) -> 1115 | F16: =IFERROR(SUM('01_Data_Model'!G38:G40),0) -> 191000 | G16: =IFERROR(SUM('01_Data_Model'!H38:H40),0) -> 26800 | H16: =IFERROR(G16/D16,0) -> 20.458015 | I16: =IFERROR((F16-G16)/G16,0) -> 6.1268657 | J16: =IFERROR(E16/D16,0) -> 0.85114504 | K16: =IFERROR(1-J16,0) -> 0.14885496 | L16: =Monthy_Metrics[[#This Row],[Revenue]]/Monthy_Metrics[[#This Row],[Active Users]]*(1/(Monthy_Metrics[[#This Row],[Churn Rate]])) -> 1150.7876

Sheet 03_Analysis_Pivots
A1: Channel | B1: (All) | H1: Month | I1: (All)
A3: Month | B3: Sum of Active Users | C3: Sum of New Users | H3: Channel | I3: Sum of Revenue | J3: Sum of Churn Rate
A4: Jan | B4: 495 | C4: 600 | H4: Google Ads | I4: 928000 | J4: 2.3354945
A5: Feb | B5: 620 | C5: 750 | H5: Instagram | I5: 467000 | J5: 1.7187307
A6: Mar | B6: 695 | C6: 830 | H6: Referrals | I6: 363000 | J6: 1.0202691
A7: Apr | B7: 780 | C7: 920 | H7: Grand Total | I7: 1758000 | J7: 5.0744943
A8: Grand Total | B8: 2590 | C8: 3100
H11: Month | I11: (All)
H13: Channel | I13: Sum of Marketing Spend | J13: Sum of ROI
H14: Google Ads | I14: 166800 | J14: 53.956328
H15: Instagram | I15: 66200 | J15: 71.359046
H16: Referrals | I16: 40800 | J16: 94.281807
H17: Grand Total | I17: 273800 | J17: 219.59718
B20: Channel | C20: (All)
B22: Row Labels | C22: Sum of Revenue | D22: Sum of Active Users | E22: Sum of New Users | F22: Sum of Marketing Spend | G22: Sum of Churn Rate | H22: Sum of CAC | I22: Sum of ROI | J22: Sum of LTV | K22: Sum of MRR
B23: Jan | C23: 85000 | D23: 495 | E23: 600 | F23: 16000 | G23: 0.43541667 | H23: 73.472222 | I23: 16 | J23: 5492.3308 | K23: 14737193
B24: Feb | C24: 102000 | D24: 620 | E24: 750 | F24: 19000 | G24: 0.43828671 | H24: 69.685315 | I24: 15.444444 | J24: 3973.0428 | K24: 17007357
B25: Mar | C25: 113000 | D25: 695 | E25: 830 | F25: 20000 | G25: 0.41596899 | H25: 66.269767 | I25: 16.440185 | J25: 4284.9304 | K25: 18634317
B26: Apr | C26: 126000 | D26: 780 | E26: 920 | F26: 21000 | G26: 0.40398551 | H26: 62.784679 | I26: 17.420513 | J26: 3893.9856 | K26: 20674300
B27: May | C27: 137000 | D27: 845 | E27: 990 | F27: 21900 | G27: 0.38554422 | H27: 60.884354 | I27: 18.31891 | J27: 4194.6838 | K27: 22560563
B28: Jun | C28: 147000 | D28: 890 | E28: 1050 | F28: 22900 | G28: 0.41254579 | H28: 60.301053 | I28: 18.485867 | J28: 3737.8947 | K28: 24654699 | L28: =GETPIVOTDATA("Sum of LTV",$B$22,"Month","Dec")-GETPIVOTDATA("Sum of LTV",$B$22,"Month","Jan") -> -1625.4756
B29: Jul | C29: 157000 | D29: 935 | E29: 1100 | F29: 23900 | G29: 0.40844722 | H29: 60.274312 | I29: 18.854406 | J29: 3854.3426 | K29: 26756479
B30: Aug | C30: 165000 | D30: 975 | E30: 1160 | F30: 24800 | G30: 0.44444444 | H30: 59.285714 | I30: 19.080702 | J30: 3482.182 | K30: 28359450
B31: Sep | C31: 172000 | D31: 1005 | E31: 1200 | F31: 25400 | G31: 0.45181733 | H31: 58.963653 | I31: 19.340407 | J31: 3524.7249 | K31: 29819849
B32: Oct | C32: 179000 | D32: 1045 | E32: 1240 | F32: 25900 | G32: 0.43738192 | H32: 58.181511 | I32: 19.707954 | J32: 3633.829 | K32: 31058185
B33: Nov | C33: 184000 | D33: 1075 | E33: 1270 | F33: 26200 | G33: 0.42676662 | H33: 57.539582 | I33: 20.013965 | J33: 3724.6778 | K33: 31901635
B34: Dec | C34: 191000 | D34: 1115 | E34: 1310 | F34: 26800 | G34: 0.41388889 | H34: 57.003968 | I34: 20.489826 | J34: 3866.8552 | K34: 33075528
B35: Grand Total | C35: 1758000 | D35: 10475 | E35: 12420 | F35: 273800 | G35: 5.0744943 | H35: 744.64613 | I35: 219.59718 | J35: 47663.48 | K35: 2.9923956e+08

Sheet 04_KPI_Engine
C4: Metric | D4: Current | E4: Previous | F4: % Change
C5: CAC | D5: =GETPIVOTDATA("Sum of CAC",'03_Analysis_Pivots'!$B$22,"Month","Dec") -> 57.003968 | E5: =GETPIVOTDATA("Sum of CAC",'03_Analysis_Pivots'!$B$22,"Month","Jan") -> 73.472222 | F5: =(D5-E5)/E5 -> -0.22414259
C6: LTV | D6: =GETPIVOTDATA("Sum of LTV",'03_Analysis_Pivots'!$B$22,"Month","Dec") -> 3866.8552 | E6: =GETPIVOTDATA("Sum of LTV",'03_Analysis_Pivots'!$B$22,"Month","Jan") -> 5492.3308 | F6: =(D6-E6)/E6 -> -0.2959537
C7: MRR | D7: =GETPIVOTDATA("Sum of MRR",'03_Analysis_Pivots'!$B$22,"Month","Dec") -> 33075528 | E7: =GETPIVOTDATA("Sum of MRR",'03_Analysis_Pivots'!$B$22,"Month","Jan") -> 14737193 | F7: =(D7-E7)/E7 -> 1.2443574
C8: Churn Rate | D8: =GETPIVOTDATA("Sum of Churn Rate",'03_Analysis_Pivots'!$B$22,"Month","Dec") -> 0.41388889 | E8: =GETPIVOTDATA("Sum of Churn Rate",'03_Analysis_Pivots'!$B$22,"Month","Jan") -> 0.43541667 | F8: =(D8-E8)/E8 -> -0.049441786

Sheet 05_Dashboard
AE4: Marketing & Growth Performance Dashboard
AK8: (Jan–Dec 2024)
AB11: KPI Cards
AE16: CAC : | AI16: LTV : | AM16: MRR : | AQ16: Churn Rate :
AE18: ="₹"&ROUND('04_KPI_Engine'!D5,0) -> ₹57 | AI18: ="₹"&ROUND('04_KPI_Engine'!D6/1000,2)&"K" -> ₹3.87K | AM18: ="₹"&ROUND('04_KPI_Engine'!D7/10000000,2)& "cr" -> ₹3.31cr | AQ18: =ROUND('04_KPI_Engine'!D8,2) -> 0.41
AF20: =" ("&IF('04_KPI_Engine'!F5<0,"▼ ","▲ ")&TEXT(ABS('04_KPI_Engine'!F5),"0.0%")&")" -> (▼ 22.4%) | AJ20: =" ("&IF('04_KPI_Engine'!F6<0,"▼ ","▲ ")&TEXT(ABS('04_KPI_Engine'!F6),"0.0%")&")" -> (▼ 29.6%) | AN20: =" ("&IF('04_KPI_Engine'!F7<0,"▼ ","▲ ")&TEXT(ABS('04_KPI_Engine'!F7),"0.0%")&")" -> (▲ 124.4%) | AR20: =" ("&IF('04_KPI_Engine'!F8<0,"▼ ","▲ ")&TEXT(ABS('04_KPI_Engine'!F8),"0.0%")&")" -> (▼ 4.9%)
AB24: Charts
AB72: Insights
AB78: 1. User Growth Trend
AB79: Active users show a consistent upward trend, peaking in December, with new users increasing by 118.3% over the year. This indicates strong acquisition momentum, likely driven by high-performing campaigns or seasonal demand.
AB83: 2. Channel Performance
AB85: A clear efficiency gap exists across channels. Referrals deliver the highest ROI, while Google Ads underperform despite high spend. This suggests inefficient budget allocation, where resources can be shifted toward high-performing channels and underperforming campaigns need optimization.
AB88: 3. Revenue Trend
AB90: Revenue increased by 124.4%, closely tracking user growth. Peak revenue aligns with campaign periods, indicating that growth is marketing-driven. However, this raises a key question around sustainability without continuous campaign spend.
AB93: 4. Churn Rate Insight
AB94: Churn improved from 44% to 41%, showing better retention. However, a spike in August highlights potential issues in customer experience or acquisition quality. Addressing such fluctuations is critical to ensure stable long-term retention.
AB97: 5. CAC & LTV Analysis
AB98: CAC decreased by 22.4%, while LTV increased by 29.6%. This indicates improving unit economics, with customers becoming more valuable and cheaper to acquire, strengthening overall profitability.
... AB103: Focus on Referrals, maintain campaigns during peak months, and implement retention strategies to further reduce churn. aScale high-ROI channels like referrals Optimize or reduce low-performing spend (Google Ads) Investigate churn spikes and improve retention strategies Focus on sustainable growth beyond campaign-driven peaks
AO109: .

Sheet Project Summary
B3: Introduction
B7: Growth analytics project for GrowX Labs — a SaaS startup aiming to optimize its marketing spend, customer lifetime value, and churn rate.
B11: KPI Highlights
B15: MRR | D15: ="₹"&ROUND('04_KPI_Engine'!D7/10000000,2)& "cr" &" ("&IF('04_KPI_Engine'!F7<0,"▼ ","▲ ")&TEXT(ABS('04_KPI_Engine'!F7),"0.0%")&")" -> ₹3.31cr (▲ 124.4%)
B18: CAC | D18: ="₹"&ROUND('04_KPI_Engine'!D5,0)&" ("&IF('04_KPI_Engine'!F5<0,"▼ ","▲ ")&TEXT(ABS('04_KPI_Engine'!F5),"0.0%")&")" -> ₹57 (▼ 22.4%)
B21: LTV | D21: ="₹"&ROUND('04_KPI_Engine'!D6/1000,2)&"K"&" ("&IF('04_KPI_Engine'!F6<0,"▼ ","▲ ")&TEXT(ABS('04_KPI_Engine'!F6),"0.0%")&")" -> ₹3.87K (▼ 29.6%)
B24: Churn rate | E24: =ROUND('04_KPI_Engine'!D8,2)&" ("&IF('04_KPI_Engine'!F8<0,"▼ ","▲ ")&TEXT(ABS('04_KPI_Engine'!F8),"0.0%")&")" -> 0.41 (▼ 4.9%)
B28: Trend Insights
B32: Active users increased by 118.3% over 12 months
B34: Highest ROI channel: Referrals
B36: Churn trend: improved over time
B41: Actionable Recommendations
B45: Reallocate budget to Referrals and Instagram
B47: Explore additional acquisition channels or promotions
B49: Scale campaigns during months with peak user growth
